glotio/__init__.py
glotio/runner.py
glotio_api-1.0.1.dist-info/METADATA
glotio_api-1.0.1.dist-info/WHEEL
glotio_api-1.0.1.dist-info/top_level.txt
glotio_api-1.0.1.dist-info/RECORD
