Metadata-Version: 2.1
Name: glotio-api
Version: 1.0.1
Summary: Python bindings for the glot.io API.
Home-page: https://github.com/raster0x2a/glotio-api
Author: raster0x2a
Author-email: raster0x2a@gmail.com
License: MIT
Keywords: glot.io api
Platform: UNKNOWN
Classifier: Programming Language :: Python :: 3.7
Requires-Python: >3.4
Requires-Dist: requests
